sccket/__init__.py
sccket/sccket.py
sccket-3.8.5.1.dist-info/METADATA
sccket-3.8.5.1.dist-info/WHEEL
sccket-3.8.5.1.dist-info/top_level.txt
sccket-3.8.5.1.dist-info/RECORD
