Metadata-Version: 2.1
Name: sccket
Version: 3.8.5.1
Summary: This package allows for HTTP NTLM authentication using the requests library.
Author: Composable HTTP middleware for requests
Classifier: Programming Language :: Python :: 3
Classifier: Operating System :: OS Independent
Classifier: License :: OSI Approved :: MIT License
